arena_interface/__about__.py
arena_interface/__init__.py
arena_interface/arena_interface.py
arena_interface/cli.py
arena_interface-3.0.0.dist-info/LICENSE
arena_interface-3.0.0.dist-info/METADATA
arena_interface-3.0.0.dist-info/WHEEL
arena_interface-3.0.0.dist-info/entry_points.txt
arena_interface-3.0.0.dist-info/top_level.txt
arena_interface-3.0.0.dist-info/RECORD
