Metadata-Version: 2.1
Name: arena-interface
Version: 3.0.0
Summary: Python interface to the Reiser lab ArenaController.
Home-page: https://github.com/janelia-python/arena_interface_python
Author: Peter Polidoro
Author-email: peter@polidoro.io
License: BSD-3-Clause
Classifier: Programming Language :: Python :: 3
License-File: LICENSE
Requires-Dist: click
Requires-Dist: schedule
Requires-Dist: pyserial
